business_central/__init__.py
business_central/client.py
business_central/py.typed
business_central/services.py
business_central/session.py
business_central-0.4.0.dist-info/METADATA
business_central-0.4.0.dist-info/WHEEL
business_central-0.4.0.dist-info/licenses/LICENSE
business_central-0.4.0.dist-info/RECORD
