Metadata-Version: 2.3
Name: business-central
Version: 0.4.0
Summary: Add your description here
Author-email: Akshay Prabhu <akshay.prabhu0398@gmail.com>
Requires-Python: >=3.12
Requires-Dist: arrow>=1.3.0
Requires-Dist: loguru>=0.7.2
Requires-Dist: openpyxl>=3.1.5
Requires-Dist: pandas>=2.2.3
Requires-Dist: requests>=2.32.3
